forecasttime/__init__.py
forecasttime/features_engineering.py
forecasttime/forecasttime.py
forecasttime/ml_pycaret.py
forecasttime/model_dev.py
forecasttime/model_eval.py
forecasttime/utils.py
forecasttime-0.0.4.dist-info/LICENSE
forecasttime-0.0.4.dist-info/METADATA
forecasttime-0.0.4.dist-info/WHEEL
forecasttime-0.0.4.dist-info/dependency_links.txt
forecasttime-0.0.4.dist-info/top_level.txt
forecasttime-0.0.4.dist-info/RECORD
